[{"m3u8": "https://videozm.whqhyg.com:8091/20200930/NraG6qZi/index.m3u8", "img": "https://img2.minqingguancha.com:8099/z-t-img/AUKG446.jpg", "title": "AUKG-446在町内会的会议上偷偷雷兹的妈妈婚外情翔田千里"}, {"m3u8": "https://videozm.whqhyg.com:8091/20200930/e6XdkQvw/index.m3u8", "img": "https://img2.minqingguancha.com:8099/z-t-img/CHN166.jpg", "title": "CHN-166新·外行姑娘，借给您。藤田澪"}, {"m3u8": "https://videozm.whqhyg.com:8091/20200930/uKW1pyX9/index.m3u8", "img": "https://img2.minqingguancha.com:8099/z-t-img/CMD023.jpg", "title": "CMD-023诱惑服装商店星级糖"}, {"m3u8": "https://videozm.whqhyg.com:8091/20200930/SgRHbOEp/index.m3u8", "img": "https://img2.minqingguancha.com:8099/z-t-img/EBOD676.jpg", "title": "EBOD-676AV一直拒绝现役☆着色情偶像终于AV解禁松泽薰"}, {"m3u8": "https://videozm.whqhyg.com:8091/20200930/CRNrnHm8/index.m3u8", "img": "https://img2.minqingguancha.com:8099/z-t-img/ESK305.jpg", "title": "ESK-305升级吧和女儿"}, {"m3u8": "https://videozm.whqhyg.com:8091/20200930/nHER8xU1/index.m3u8", "img": "https://img2.minqingguancha.com:8099/z-t-img/HAWA165.jpg", "title": "HAWA-165外行妻子到大学生变态觉醒的巨乳妻子三島奈津子"}, {"m3u8": "https://videozm.whqhyg.com:8091/20200930/qIcoBYY2/index.m3u8", "img": "https://img2.minqingguancha.com:8099/z-t-img/HBAD458.jpg", "title": "HBAD-458桃尻寡妇亲属棒的俘虏人生最大的追击升天大浦真奈美"}, {"m3u8": "https://videozm.whqhyg.com:8091/20200930/wsZjzDmz/index.m3u8", "img": "https://img2.minqingguancha.com:8099/z-t-img/HUSR170.jpg", "title": "HUSR-170向女儿展示了日本大男孩的性骚扰的结果，"}, {"m3u8": "https://videojccdn.wzj9.com:8091/20201011/jufd00175-Part-3/index.m3u8", "img": "https://jc.8f23aa8.com/2020/02/jufd00175.jpg", "title": "JUFD-175 着衣で濡れ透ける巨乳ノーブラ妻 北川瞳-C"}, {"m3u8": "https://videojccdn.wzj9.com:8091/20201011/jufd00175-Part-2/index.m3u8", "img": "https://jc.8f23aa8.com/2020/02/jufd00175.jpg", "title": "JUFD-175 着衣で濡れ透ける巨乳ノーブラ妻 北川瞳-B"}, {"m3u8": "https://videojccdn.wzj9.com:8091/20201011/jufd00175-Part-1/index.m3u8", "img": "https://jc.8f23aa8.com/2020/02/jufd00175.jpg", "title": "JUFD-175 着衣で濡れ透ける巨乳ノーブラ妻 北川瞳-A"}, {"m3u8": "https://videozm.whqhyg.com:8091/20201002/XbUQOdvQ/index.m3u8", "img": "https://img2.minqingguancha.com:8099/z-t-img/URMC023.jpg", "title": "URMC-023姐姐的爆乳太下流了，音海里奈"}, {"m3u8": "https://videozm.whqhyg.com:8091/20201002/gIcutyxC/index.m3u8", "img": "https://img2.minqingguancha.com:8099/z-t-img/STARS025.jpg", "title": "STARS-025凛然虚幻的七海蒂娜AV DEBUT"}, {"m3u8": "https://videozm.whqhyg.com:8091/20201002/FCVCfWuC/index.m3u8", "img": "https://img2.minqingguancha.com:8099/z-t-img/STARS023.jpg", "title": "STARS-023唯井麻痹18岁的嘴唇纠缠在一起的舌特浓维罗丘发情SEX"}, {"m3u8": "https://videozm.whqhyg.com:8091/20201002/JSMcip9E/index.m3u8", "img": "https://img2.minqingguancha.com:8099/z-t-img/STARS021.jpg", "title": "STARS-021桐谷节毕业早泄大爱风俗小姐"}, {"m3u8": "https://videozm.whqhyg.com:8091/20201002/08wyH7et/index.m3u8", "img": "https://img2.minqingguancha.com:8099/z-t-img/SPRD1101.jpg", "title": "SPRD-1101母奸中出儿子第一次被出狱的母亲藤咲美冬"}, {"m3u8": "https://videozm.whqhyg.com:8091/20201002/EvNiU4yo/index.m3u8", "img": "https://img2.minqingguancha.com:8099/z-t-img/SPRD1100.jpg", "title": "SPRD-1100儿子媳妇和继父佐佐木秋"}, {"m3u8": "https://videozm.whqhyg.com:8091/20201002/qKQzHaiJ/index.m3u8", "img": "https://img2.minqingguancha.com:8099/z-t-img/MKMP257.jpg", "title": "MKMP-257小时停止女主播王妃月度新闻节目直播中停时间现场推出"}, {"m3u8": "https://videozm.whqhyg.com:8091/20201002/YLHMtW8a/index.m3u8", "img": "https://img2.minqingguancha.com:8099/z-t-img/MIFD063.jpg", "title": "MIFD-063比模特更瘦和屁股更漂亮的巨乳公司职员 日向惠美"}, {"m3u8": "https://videozm.whqhyg.com:8091/20201002/q5aC55o4/index.m3u8", "img": "https://img2.minqingguancha.com:8099/z-t-img/MIFD062.jpg", "title": "MIFD-062新人超敏感有点酷的超小姐美少女轻音现役女大学生AV出道冈本真忧"}, {"m3u8": "https://videozm.whqhyg.com:8091/20201002/RFW7YAwg/index.m3u8", "img": "https://img2.minqingguancha.com:8099/z-t-img/MIDE617.jpg", "title": "MIDE-617阴道中(娜卡)×阴道深处(奥克)×全身绝顶3正式文档志田雪奈"}, {"m3u8": "https://videozm.whqhyg.com:8091/20201002/s5Hsu3TD/index.m3u8", "img": "https://img2.minqingguancha.com:8099/z-t-img/MIDE616.jpg", "title": "MIDE-616随时随地立即哈美女仆有季"}, {"m3u8": "https://videozm.whqhyg.com:8091/20201002/VI96TvXV/index.m3u8", "img": "https://img2.minqingguancha.com:8099/z-t-img/MIDE615.jpg", "title": "MIDE-615春药油流氓~因强制发情而闷闷不乐的绝顶化~花蕾"}, {"m3u8": "https://videozm.whqhyg.com:8091/20201002/1Kr2VMtH/index.m3u8", "img": "https://img2.minqingguancha.com:8099/z-t-img/MIDE614.jpg", "title": "MIDE-614每天射精10次也不会停止的高潮SEX特别七泽美"}, {"m3u8": "https://videojccdn.wzj9.com:8091/20201011/jufd00189-Part-2/index.m3u8", "img": "https://jc.8f23aa8.com/2020/02/jufd00189.jpg", "title": "JUFD-189 夫の性癖を満足させるために躾けられる豊満妻～ りょうこ-B"}, {"m3u8": "https://videojccdn.wzj9.com:8091/20201011/jufd00189-Part-1/index.m3u8", "img": "https://jc.8f23aa8.com/2020/02/jufd00189.jpg", "title": "JUFD-189 夫の性癖を満足させるために躾けられる豊満妻～ りょうこ-A"}, {"m3u8": "https://videojccdn.wzj9.com:8091/20201011/jufd00183-Part-3/index.m3u8", "img": "https://jc.8f23aa8.com/2020/02/jufd00183.jpg", "title": "JUFD-183 敏感な乳房が咽び泣く院内調教～ 仁科百華-C"}, {"m3u8": "https://videojccdn.wzj9.com:8091/20201011/jufd00183-Part-2/index.m3u8", "img": "https://jc.8f23aa8.com/2020/02/jufd00183.jpg", "title": "JUFD-183 敏感な乳房が咽び泣く院内調教～ 仁科百華-B"}, {"m3u8": "https://videojccdn.wzj9.com:8091/20201011/jufd00183-Part-1/index.m3u8", "img": "https://jc.8f23aa8.com/2020/02/jufd00183.jpg", "title": "JUFD-183 敏感な乳房が咽び泣く院内調教～ 仁科百華"}, {"m3u8": "https://videozm.whqhyg.com:8091/20201002/N6C96ncU/index.m3u8", "img": "https://img2.minqingguancha.com:8099/z-t-img/MEYD462.jpg", "title": "MEYD-462我其实一直被丈夫的上司侵犯…。大浦真奈美"}, {"m3u8": "https://videozm.whqhyg.com:8091/20201002/sDcWBvXJ/index.m3u8", "img": "https://img2.minqingguancha.com:8099/z-t-img/MEYD461.jpg", "title": "MEYD-461人有妻子也不介意猛追活塞的迟漏0普魔黑川堇"}, {"m3u8": "https://videozm.whqhyg.com:8091/20201002/rXKV1xpV/index.m3u8", "img": "https://img2.minqingguancha.com:8099/z-t-img/MEYD-460.jpg", "title": "MEYD-460传说中的超高级中出索普松永"}, {"m3u8": "https://videozm.whqhyg.com:8091/20201002/GnoNMROR/index.m3u8", "img": "https://img2.minqingguancha.com:8099/z-t-img/MEYD459.jpg", "title": "MEYD-459秘密委托老公弟弟代种的期盼中出欲妻不贞东凛"}, {"m3u8": "https://videozm.whqhyg.com:8091/20201002/svDFe352/index.m3u8", "img": "https://img2.minqingguancha.com:8099/z-t-img/MEYD458.jpg", "title": "MEYD-458忘年会NTR~一滴也不能喝酒的妻子"}, {"m3u8": "https://videozm.whqhyg.com:8091/20201002/P6n11KUX/index.m3u8", "img": "https://img2.minqingguancha.com:8099/z-t-img/MEYD457.jpg", "title": "MEYD-457人妻怀孕只瞄准危险日看不见脸×普魔榎本美咲"}]