[{"m3u8": "https://video.lsnbf.com/20220809/M2E2ZWUxND/101332/720/hls/encrypt/index.m3u8", "img": "https://www.haocai1688.com/pic/uploadimg/2022/04/220707ym157.mp4.jpg", "title": "MRXD-088 美尻獵人 3 狂拍巨尻素人妻"}, {"m3u8": "https://video.lsnbf.com/20220809/ZmZiYTQxMG/101002/720/hls/encrypt/index.m3u8", "img": "https://www.haocai1688.com/pic/uploadimg/2022/04/220707ym158.mp4.jpg", "title": "MRXD-089 真實貼拍檔案！與型男的私密關係全都錄！阿部美佳子"}, {"m3u8": "https://video.lsnbf.com/20220809/MTQ2N2I4ZD/101711/720/hls/encrypt/index.m3u8", "img": "https://www.haocai1688.com/pic/uploadimg/2022/04/220707ym159.mp4.jpg", "title": "MUDR-039 原作改編 妹妹天堂 3 與5位妹妹每天肏到爽 2"}, {"m3u8": "https://video.lsnbf.com/20220809/ZTY0NDMyZG/101731/720/hls/encrypt/index.m3u8", "img": "https://www.haocai1688.com/pic/uploadimg/2022/04/220707ym160.mp4.jpg", "title": "NGOD-075 人妻被愛稱讚人的鄰居肏翻睡走 阿部栞菜"}, {"m3u8": "https://video.lsnbf.com/20220809/NDk2MjlhMz/102105/720/hls/encrypt/index.m3u8", "img": "https://www.haocai1688.com/pic/uploadimg/2022/04/220707ym161.mp4.jpg", "title": "NHDTB-134 中出幹翻沒穿內褲的土下座謝罪OL菊花 4"}, {"m3u8": "https://video.zmwbf.com/20220808/ODA0MWU0ZD/184754/1280/hls/encrypt/index.m3u8", "img": "https://img2.minqingguancha.com:8099/z-t-img/VDD145.jpg", "title": "VDD-145接待员in…。[恐吓套房]皆野爱。"}, {"m3u8": "https://video.zmwbf.com/20220808/MmE3NmE2Yz/175942/1280/hls/encrypt/index.m3u8", "img": "https://img2.minqingguancha.com:8099/z-t-img/TEEK001.jpg", "title": "TEEK-001流氓电车耻辱OL通勤篇被色狼持续侵犯沉溺于巨乳OL音海里奈。"}, {"m3u8": "https://video.zmwbf.com/20220808/NmFhZjJkYT/181313/1280/hls/encrypt/index.m3u8", "img": "https://img2.minqingguancha.com:8099/z-t-img/ADN203.jpg", "title": "ADN-203不成熟奸情年下下属和人妻OL松下纱荣子。"}, {"m3u8": "https://video.zmwbf.com/20220808/MmNjODIyZT/182924/1280/hls/encrypt/index.m3u8", "img": "https://img2.minqingguancha.com:8099/z-t-img/ATID-339.jpg", "title": "ATID-339接待小姐的潮湿面包花绽放。"}, {"m3u8": "https://video.zmwbf.com/20220808/MjJjMzE3Y2/184214/1280/hls/encrypt/index.m3u8", "img": "https://img2.minqingguancha.com:8099/z-t-img/WZEN-021.jpg", "title": "WZEN-021追奸。"}, {"m3u8": "https://video.zmwbf.com/20220808/MGE0NmNlOT/185255/1280/hls/encrypt/index.m3u8", "img": "https://img2.minqingguancha.com:8099/z-t-img/JUFE-036.jpg", "title": "JUFE-036肉感紧身衣！高挑美女OL粗俗的衣着SEX~回归职场的人妻OL朝阳~水野朝阳。"}, {"m3u8": "https://video.zmwbf.com/20220808/MDUyMWY2Yj/182659/1280/hls/encrypt/index.m3u8", "img": "https://img2.minqingguancha.com:8099/z-t-img/STAR947.jpg", "title": "STAR-947户田真琴偷拍狂热者的家里蹲哥哥的性欲处理被当成玩具的美女OL"}, {"m3u8": "https://video.myzybo.com/20220725/NzE2ZTkzYT/093905/1280/hls/encrypt/index.m3u8", "img": "https://imagetupian.nypd520.com/uploads/2022/01/220601ym353.jpg", "title": "ROYD-075 與無防備過頭巨乳妹妹眼光不知放哪裡的超狹窄房間同居性活 沙月芽衣"}, {"m3u8": "https://video.myzybo.com/20220725/NjIzOTNiZm/094055/1280/hls/encrypt/index.m3u8", "img": "https://imagetupian.nypd520.com/uploads/2022/01/220601ym354.jpg", "title": "SABA-732 和錯過末班電車醉酒的同事在賓館拼房…毫無防備的模樣讓人無法忍耐…Vol.013"}, {"m3u8": "https://video.myzybo.com/20220725/ZGMxZDQzM2/094207/1280/hls/encrypt/index.m3u8", "img": "https://imagetupian.nypd520.com/uploads/2022/01/220601ym355.jpg", "title": "SCOP-745 叫來應召女郎發現的事實！ ！白天沉穩成熟的公寓鄰居變身下流淫蕩的巨乳應召女郎嬢 夜晚出現在我的面前"}, {"m3u8": "https://video.myzybo.com/20220725/YjhjOTM5Zm/094227/1280/hls/encrypt/index.m3u8", "img": "https://imagetupian.nypd520.com/uploads/2022/01/220601ym356.jpg", "title": "SCPX-436 公公突然的吻實在太贊讓認真媳婦瞬間發情雌化"}, {"m3u8": "https://video.myzybo.com/20220725/MDVhZWViOG/094303/1280/hls/encrypt/index.m3u8", "img": "https://imagetupian.nypd520.com/uploads/2022/01/220601ym357.jpg", "title": "SDAB-203 性慾強烈的想要的美少女過於焦躁的狀態下第一次的小穴高潮…內射解禁青春時代 桃乃玲"}, {"m3u8": "https://video.myzybo.com/20220725/OGZiNWIyNT/094346/1280/hls/encrypt/index.m3u8", "img": "https://imagetupian.nypd520.com/uploads/2022/01/220601ym358.jpg", "title": "SDDE-657 SOD出道的青春美少女桃乃玲期待內射解禁。"}, {"m3u8": "https://video.myzybo.com/20220725/ZjI2NzMyNj/094418/1280/hls/encrypt/index.m3u8", "img": "https://imagetupian.nypd520.com/uploads/2022/01/220601ym359.jpg", "title": "SDDE-658【全部都是自拍影片】畢業旅行中被很多男人上的紀錄片 新井里真"}, {"m3u8": "https://video.myzybo.com/20220725/Mzk1YWUwMz/094441/1280/hls/encrypt/index.m3u8", "img": "https://imagetupian.nypd520.com/uploads/2022/01/220601ym360.jpg", "title": "SDJS-130 在人事部工作6個月的田中21歲，有親和力的性格很可愛，經驗也很少，但實際上因為太過喜歡色情，在風俗店工作過，是原人氣洗浴小姐。？好像…色情的事積極的過頭AV演出(心)了！"}, {"m3u8": "https://video.myzybo.com/20220725/ZDEzNGU5Yj/094557/1280/hls/encrypt/index.m3u8", "img": "https://imagetupian.nypd520.com/uploads/2022/01/220601ym361.jpg", "title": "SDMU-968 青春之光森田哲矢製作總指揮民宿殺人事件"}, {"m3u8": "https://video.myzybo.com/20220725/ZDRlZjY0MG/094631/1280/hls/encrypt/index.m3u8", "img": "https://imagetupian.nypd520.com/uploads/2022/01/220601ym362.jpg", "title": "SDNM-307 婚後太無聊人妻找刺激AV出到綁著4P輪插爽上癮還... 椿こはる"}, {"m3u8": "https://video.myzybo.com/20220725/Y2EwMWQxZT/094806/1280/hls/encrypt/index.m3u8", "img": "https://imagetupian.nypd520.com/uploads/2022/01/220601ym363.jpg", "title": "SDNM-316 椿小春 26歳 第2章 強迫口交・拘束・然後初次放尿"}, {"m3u8": "https://video.myzybo.com/20220725/MDM3MmY5Nm/094846/1280/hls/encrypt/index.m3u8", "img": "https://imagetupian.nypd520.com/uploads/2022/01/220601ym364.jpg", "title": "SDTH-012 女大生喜歡野外車上被人插5P狂插爽到射進去 ケモケモ蓮"}, {"m3u8": "https://video.myzybo.com/20220725/MmMzMDRiYm/094930/1280/hls/encrypt/index.m3u8", "img": "https://imagetupian.nypd520.com/uploads/2022/01/220601ym365.jpg", "title": "SHKD-978 潛入搜查官、直到墮落… 白鳥南"}, {"m3u8": "https://video.myzybo.com/20220725/NzJjYTliZT/095019/1280/hls/encrypt/index.m3u8", "img": "https://imagetupian.nypd520.com/uploads/2022/01/220601ym366.jpg", "title": "SHKD-979 足球部女經理毎天幫顧問教師性處理。 堀北灣"}, {"m3u8": "https://video.myzybo.com/20220725/MDFjMzQzN2/095139/1280/hls/encrypt/index.m3u8", "img": "https://imagetupian.nypd520.com/uploads/2022/01/220601ym367.jpg", "title": "SHKD-982 被打工處新人大叔侵犯的前輩女大生 沙月惠奈"}, {"m3u8": "https://video.myzybo.com/20220725/YjNlNGMxZm/095134/1280/hls/encrypt/index.m3u8", "img": "https://imagetupian.nypd520.com/uploads/2022/01/220601ym368.jpg", "title": "SHKD-984 想說是朋友的只有你嗎？w 這種惡劣女人讓人盡情強暴也無妨 希代亞美"}, {"m3u8": "https://video.myzybo.com/20220725/M2FmYjczNz/095254/1280/hls/encrypt/index.m3u8", "img": "https://imagetupian.nypd520.com/uploads/2022/01/220601ym369.jpg", "title": "SPRD-1478 旅途中再見熟繼母 田所百合"}, {"m3u8": "https://video.jcwbf.com/20220815/ODRjNzk2OW/003314/1280/hls/encrypt/index.m3u8", "img": "https://jc.8f23aa8.com/2022/01/15dss00164.jpg", "title": "15dss00164 GET！素人ナンパ スキー・ゲレンデ・軽井沢No.164"}, {"m3u8": "https://video.jcwbf.com/20220815/ZmZiYTI3ZD/003936/1280/hls/encrypt/index.m3u8", "img": "https://jc.8f23aa8.com/2022/01/15dss00167.jpg", "title": "15dss00167 GET！素人ナンパ美少女限定祭り～ご当地ユーザーが選んだ！ムチャクチャ可愛い娘！20人～"}, {"m3u8": "https://video.zmwbf.com/20220808/Nzc3MzYyMD/174739/1280/hls/encrypt/index.m3u8", "img": "https://img2.minqingguancha.com:8099/z-t-img/JUFE003.jpg", "title": "JUFE-003寸阻止淫语巨尻女同性恋部长的妻子一边被焦急一边被禁断的快乐拖拽…。筱田"}, {"m3u8": "https://video.zmwbf.com/20220808/NjViOTI1Mz/183331/1280/hls/encrypt/index.m3u8", "img": "https://img2.minqingguancha.com:8099/z-t-img/JUFE-029.jpg", "title": "JUFE-029肉感紧身衣！高挑美女OL的粗俗衣着SEX~回归职场的人妻OL·爱美美~黑宫爱美。"}, {"m3u8": "https://video.zmwbf.com/20220808/NjAyZmJkMm/174937/1280/hls/encrypt/index.m3u8", "img": "https://img2.minqingguancha.com:8099/z-t-img/JUFE009.jpg", "title": "JUFE-009高飞车女社长屁股肉饿失禁道歉~被喝了利尿剂羞耻的奥西科调教~筱田优。"}, {"m3u8": "https://video.zmwbf.com/20220808/OGE5NTE1OW/174714/1280/hls/encrypt/index.m3u8", "img": "https://img2.minqingguancha.com:8099/z-t-img/JUY719.jpg", "title": "JUY-719 应该和女儿童贞卡莱西练习 但是被好几次都停不下来的失控机车觉醒了！"}, {"m3u8": "https://video.zmwbf.com/20220808/ZTVmYjc2Mz/190633/1280/hls/encrypt/index.m3u8", "img": "https://img2.minqingguancha.com:8099/z-t-img/NKKD109.jpg", "title": "NKKD-109这次我的妻子(36岁)被临时工的打工君(20岁)盯上了…"}]