[{"m3u8": "https://videozm.whqhyg.com:8091/20220321/G2Qgut73/index.m3u8", "img": "https://img2.minqingguancha.com:8099/z-t-img/ATID-360.jpg", "title": "ATID-360劫持犯THE Longest Day。"}, {"m3u8": "https://videozm.whqhyg.com:8091/20220321/2pTarPsh/index.m3u8", "img": "https://img2.minqingguancha.com:8099/z-t-img/ATID-362.jpg", "title": "ATID-362办公室女士的潮湿面包织笠玩具。"}, {"m3u8": "https://videozm.whqhyg.com:8091/20220321/1WiRETbd/index.m3u8", "img": "https://img2.minqingguancha.com:8099/z-t-img/BIJN-161.jpg", "title": "BIJN-161性欲太强的美女熟女太舒服了，忍不住“请疯了. 片濑仁美。"}, {"m3u8": "https://videozm.whqhyg.com:8091/20220322/znjgHum2/index.m3u8", "img": "https://img2.minqingguancha.com:8099/z-t-img/BIJN-162.jpg", "title": "BIJN-162可爱的妻子在眼前快乐狂乱认真感受的样子！ 加藤"}, {"m3u8": "https://videozm.whqhyg.com:8091/20220321/92RzG4jm/index.m3u8", "img": "https://img2.minqingguancha.com:8099/z-t-img/BLK-417.jpg", "title": "BLK-417瞄准她移开视线的一瞬间的机会用短时间的口交偷偷地偷懒吧深田爱美。"}, {"m3u8": "https://videozm.whqhyg.com:8091/20220321/pgWaDv00/index.m3u8", "img": "https://img2.minqingguancha.com:8099/z-t-img/BLK-418.jpg", "title": "BLK-418被卖给男朋友的狂妄辣妹！老爸专用瞪着中出肉马桶咲原林。"}, {"m3u8": "https://videozm.whqhyg.com:8091/20220321/UdOLXAhV/index.m3u8", "img": "https://img2.minqingguancha.com:8099/z-t-img/CHERD-69.jpg", "title": "CHERD-69“第一次和阿姨一起出生是不是？“童贞君和人妻熟女最好的笔下性交青井玛丽。"}, {"m3u8": "https://videojccdn.wzj9.com:8091/20220359/149rd00747/index.m3u8", "img": "https://jc.8f23aa8.com/2022/01/149rd00747.jpg", "title": "149rd00747 街で出会った清楚妻を車に連れ込みくどき落としてラブホでヌキまくり！いくつになっても女でいたいの ここだってほら、こんなに濡れてるの"}, {"m3u8": "https://videozm.whqhyg.com:8091/20220321/BUHmqnAk/index.m3u8", "img": "https://img2.minqingguancha.com:8099/z-t-img/DASD-567.jpg", "title": "DASD-567小时的女大学生在逗号0秒内浓缩鼎盛的同时被中途出走。神"}, {"m3u8": "https://videozm.whqhyg.com:8091/20220321/gYbi0ZV7/index.m3u8", "img": "https://img2.minqingguancha.com:8099/z-t-img/DASD-568.jpg", "title": "DASD-568催眠洗脑的媚肉雌性虽然讨厌却成了淫乱的维奇。稻场Luya桐岛里的。"}, {"m3u8": "https://videozm.whqhyg.com:8091/20220321/zbhwSKlO/index.m3u8", "img": "https://img2.minqingguancha.com:8099/z-t-img/DASD-570.jpg", "title": "DASD-570“忍耐5分钟给你做SEX”无法抵抗的早泄射精鞭子大姐的卧床不起的技巧筱崎。"}, {"m3u8": "https://videozm.whqhyg.com:8091/20220321/QXO4vsLD/index.m3u8", "img": "https://img2.minqingguancha.com:8099/z-t-img/DASD-572.jpg", "title": "DASD-572近亲卧床伯父相奸。使女儿骤变的没有道德的巨根。永濑结衣。"}, {"m3u8": "https://videozm.whqhyg.com:8091/20220321/njjm6wwU/index.m3u8", "img": "https://img2.minqingguancha.com:8099/z-t-img/DASD-574.jpg", "title": "DASD-574被丈夫上司迷住的人妻。剧烈活塞的黑光阴茎。人妻黑人ntr星奈爱。"}, {"m3u8": "https://videozm.whqhyg.com:8091/20220321/zSyRveKR/index.m3u8", "img": "https://img2.minqingguancha.com:8099/z-t-img/DASD-575.jpg", "title": "DASD-575黑人家庭寄宿NTR女儿的男朋友的裤裆上受欢迎肤色的马0子篇赤濑尚子。"}, {"m3u8": "https://videozm.whqhyg.com:8091/20220321/H9zlPDeS/index.m3u8", "img": "https://img2.minqingguancha.com:8099/z-t-img/DDOB-056.jpg", "title": "DDOB-056美臀妈妈vs德卡玛拉男人让妈妈抽0波汁吧！黑川堇。"}, {"m3u8": "https://videozm.whqhyg.com:8091/20220322/whYTi9I9/index.m3u8", "img": "https://img2.minqingguancha.com:8099/z-t-img/DOCP-166.jpg", "title": "DOCP-166 精子一次又一次地被屁射精的女人。"}, {"m3u8": "https://videozm.whqhyg.com:8091/20220322/0w49vHNF/index.m3u8", "img": "https://img2.minqingguancha.com:8099/z-t-img/DVDMS-431.jpg", "title": "DVDMS-431 “绝对不会有女朋友出轨，自信满满的男朋友亲自提议！ 反复发生外遇吗！？"}, {"m3u8": "https://videozm.whqhyg.com:8091/20220322/RyQys7Mt/index.m3u8", "img": "https://img2.minqingguancha.com:8099/z-t-img/DVDMS-433.jpg", "title": "DVDMS-433 初次见面，巨根被扭住了， ！穿着超活塞制服真的很棒！！in池袋。"}, {"m3u8": "https://videojccdn.wzj9.com:8091/20220359/151co04796/index.m3u8", "img": "https://jc.8f23aa8.com/2022/01/151co04796.jpg", "title": "151co04796 発情Bath Room！！ 洗っても洗ってもヌルヌルの熱い陰唇"}, {"m3u8": "https://videojccdn.wzj9.com:8091/20220359/151re00477/index.m3u8", "img": "https://jc.8f23aa8.com/2022/01/151re00477.jpg", "title": "151re00477 本番即ハメ面接で剥かれた人妻の本性！！ビラビラ痙攣・限界知らずの美人妻"}, {"m3u8": "https://videozm.whqhyg.com:8091/20220322/cEnBhQcL/index.m3u8", "img": "https://img2.minqingguancha.com:8099/z-t-img/DVDMS-436.jpg", "title": "DVDMS-436 不计其数的JD虽然被大量的精液吓得心跳加速，但却被奥玛 子淋湿了……。"}, {"m3u8": "https://videozm.whqhyg.com:8091/20220322/SUFmtrt4/index.m3u8", "img": "https://img2.minqingguancha.com:8099/z-t-img/DVDMS-438.jpg", "title": "DVDMS-438一般男女监控AV家里蹲男0学生烦恼解决企划"}, {"m3u8": "https://videozm.whqhyg.com:8091/20220321/J0siiZNn/index.m3u8", "img": "https://img2.minqingguancha.com:8099/z-t-img/EMOT-003.jpg", "title": "EMOT-003完全主观享受麻里梨和夏天的新婚生活。"}, {"m3u8": "https://videozm.whqhyg.com:8091/20220322/XjRTwTcZ/index.m3u8", "img": "https://img2.minqingguancha.com:8099/z-t-img/EYAN-140.jpg", "title": "EYAN-140丰满H杯激鞭巨尻高雅却大棒助平身体原空姐人妻AV出道朝仓风平平平体。"}, {"m3u8": "https://videozm.whqhyg.com:8091/20220322/cG9tBAVt/index.m3u8", "img": "https://img2.minqingguancha.com:8099/z-t-img/EYAN-141.jpg", "title": "EYAN-141 秋田诞生的终极吊钟型H杯！神乳若妻美云爱梨"}, {"m3u8": "https://videozm.whqhyg.com:8091/20220322/vEBQldTl/index.m3u8", "img": "https://img2.minqingguancha.com:8099/z-t-img/GDHH-162.jpg", "title": "GDHH-162 最近开始流行的美臀训练的姐姐，隔着紧身衣的布丁突出的屁股…。"}, {"m3u8": "https://videozm.whqhyg.com:8091/20220321/Vw9eNCHD/index.m3u8", "img": "https://img2.minqingguancha.com:8099/z-t-img/GDHH-164.jpg", "title": "GDHH-164 “姐姐，你在插！“”插什么啊……。"}, {"m3u8": "https://videozm.whqhyg.com:8091/20220322/Ze6L4ySL/index.m3u8", "img": "https://img2.minqingguancha.com:8099/z-t-img/HBAD-492.jpg", "title": "HBAD-492在学校和老师…。年轻的身体有村 被爱上了女生"}, {"m3u8": "https://videozm.whqhyg.com:8091/20220321/0Far1FqQ/index.m3u8", "img": "https://img2.minqingguancha.com:8099/z-t-img/HBAD-494.jpg", "title": "HBAD-494儿子的朋友Masashigaki都被性处理了沾满精液的母亲~森林。"}, {"m3u8": "https://videozm.whqhyg.com:8091/20220321/iEZ0KWH8/index.m3u8", "img": "https://img2.minqingguancha.com:8099/z-t-img/HOKS-040.jpg", "title": "HOKS-040四十岁的妓女高濑智香。"}, {"m3u8": "https://videojccdn.wzj9.com:8091/20220359/151re00503/index.m3u8", "img": "https://jc.8f23aa8.com/2022/01/151re00503.jpg", "title": "151re00503 惚れっぽく濡れやすい巨乳妻「本番面接」淫靡な瞳でフェラする限界知らずの潮吹き妻"}, {"m3u8": "https://videozm.whqhyg.com:8091/20220322/LCVDRRnz/index.m3u8", "img": "https://img2.minqingguancha.com:8099/z-t-img/HUNTA-633.jpg", "title": "被HUNTA-633 父母再婚后新生的姐夫和妹子。因为房间很小，所以可以新居...。"}, {"m3u8": "https://videozm.whqhyg.com:8091/20220321/OZLKCDsr/index.m3u8", "img": "https://img2.minqingguancha.com:8099/z-t-img/IENF-019.jpg", "title": "IENF-019经常性交哈莱姆美容3。"}, {"m3u8": "https://videozm.whqhyg.com:8091/20220322/wYpavNPu/index.m3u8", "img": "https://img2.minqingguancha.com:8099/z-t-img/IENF-021.jpg", "title": "IENF-021对不会同情我的女高中生的妹妹说“我只是擦擦而已”的约定让她赤手空拳，彼"}, {"m3u8": "https://videozm.whqhyg.com:8091/20220322/q7EsXfu4/index.m3u8", "img": "https://img2.minqingguancha.com:8099/z-t-img/IPX-352.jpg", "title": "IPX-352中年喜欢的文学美少女在无法动弹的状态下慢慢地被粘稠痴女。枫凯伦。"}, {"m3u8": "https://videozm.whqhyg.com:8091/20220322/RdN52wxQ/index.m3u8", "img": "https://img2.minqingguancha.com:8099/z-t-img/IPX-353.jpg", "title": "IPX-353 1个月禁欲在她不在的几天里和她的好友疯狂地专心做爱的樱空也共计8次密着性交！"}]