[{"m3u8": "https://videojccdn.wzj9.com:8091/20200403/qKbG40kc/index.m3u8", "img": "https://img2.minqingguancha.com:8099/z-t-img/HEYZO-0463.jpg", "title": "HEYZO-0463好奇心全开AV出演"}, {"m3u8": "https://videojccdn.wzj9.com:8091/20200403/F39ouB2a/index.m3u8", "img": "https://img2.minqingguancha.com:8099/z-t-img/HEYZO-0464.jpg", "title": "HEYZO-04644P中出大满足"}, {"m3u8": "https://videojccdn.wzj9.com:8091/20200403/yijRe1LY/index.m3u8", "img": "https://img2.minqingguancha.com:8099/z-t-img/HEYZO-0465.jpg", "title": "HEYZO-0465背徳性交女上司"}, {"m3u8": "https://videojccdn.wzj9.com:8091/20200403/6stdbQdd/index.m3u8", "img": "https://img2.minqingguancha.com:8099/z-t-img/HEYZO-0466.jpg", "title": "HEYZO-0466未知她的性秘密"}, {"m3u8": "https://videozm.whqhyg.com:8091/20200510/UZ2z0pBK/index.m3u8", "img": "https://jc.8f23aa8.com/z-t-img/SIRO-4056.jpg", "title": "SIRO-4056雪白肌肤20岁巨乳保育士的淫乱本性"}, {"m3u8": "https://videozm.whqhyg.com:8091/20200510/blX63T1p/index.m3u8", "img": "https://jc.8f23aa8.com/z-t-img/SMBD-58.jpg", "title": "SMBD-58萝莉女优爱里未来的无码内射性爱"}, {"m3u8": "https://videozm.whqhyg.com:8091/20200510/jQZ8Azwg/index.m3u8", "img": "https://jc.8f23aa8.com/z-t-img/SNIS-237.jpg", "title": "SNIS-237穿上亲手设计的高级内衣用身体上位的巨乳女OL梦乃爱华"}, {"m3u8": "https://videozm.whqhyg.com:8091/20200510/jct6gAHP/index.m3u8", "img": "https://jc.8f23aa8.com/z-t-img/SSNI-769.jpg", "title": "SSNI-769深夜零点妻子熟睡后被她借助的巨乳姐姐奥田咲"}, {"m3u8": "https://videozm.whqhyg.com:8091/20200510/w6u7x6yn/index.m3u8", "img": "https://jc.8f23aa8.com/z-t-img/SOE-446.jpg", "title": "SOE-446带着新买的相机去旅行记录下可爱巨乳女优麻美由真"}, {"m3u8": "https://videozm.whqhyg.com:8091/20200510/DwNGo5Zg/index.m3u8", "img": "https://jc.8f23aa8.com/z-t-img/SOE-430.jpg", "title": "SOE-430处男大作战可爱女优麻美由真出动讯息童贞"}, {"m3u8": "https://videozm.whqhyg.com:8091/20200510/ITys3XfJ/index.m3u8", "img": "https://jc.8f23aa8.com/z-t-img/SNIS-651.jpg", "title": "SNIS-651在夜班巴士偷偷的和素人乘客做 明日花绮罗"}, {"m3u8": "https://videojccdn.wzj9.com:8091/20200403/VQMK9Py1/index.m3u8", "img": "https://img2.minqingguancha.com:8099/z-t-img/HEYZO-0467.jpg", "title": "HEYZO-0467温泉旅情大兴奋"}, {"m3u8": "https://videojccdn.wzj9.com:8091/20200403/AjAe3zmc/index.m3u8", "img": "https://img2.minqingguancha.com:8099/z-t-img/HEYZO-0468.jpg", "title": "HEYZO-0468快楽愿望的絶顶体験"}, {"m3u8": "https://videojccdn.wzj9.com:8091/20200403/ttrdi5D1/index.m3u8", "img": "https://img2.minqingguancha.com:8099/z-t-img/HEYZO-0470.jpg", "title": "HEYZO-0470憧憬姐姐的羞耻的蜜汁"}, {"m3u8": "https://videojccdn.wzj9.com:8091/20200403/4vIc7KoT/index.m3u8", "img": "https://img2.minqingguancha.com:8099/z-t-img/HEYZO-0471.jpg", "title": "HEYZO-0471男人都想得到的爆乳"}, {"m3u8": "https://videojccdn.wzj9.com:8091/20200403/vKeVlUPo/index.m3u8", "img": "https://img2.minqingguancha.com:8099/z-t-img/HEYZO-0472.jpg", "title": "HEYZO-0472人妻治腰实态映像流出"}, {"m3u8": "https://videojccdn.wzj9.com:8091/20200403/UnPvGujH/index.m3u8", "img": "https://img2.minqingguancha.com:8099/z-t-img/HEYZO-0473.jpg", "title": "HEYZO-0473淫乱女教师的后辈指导"}, {"m3u8": "https://videojccdn.wzj9.com:8091/20200403/fhoIq5ig/index.m3u8", "img": "https://img2.minqingguancha.com:8099/z-t-img/HEYZO-0474.jpg", "title": "HEYZO-0474美爆乳和无毛的兴奋"}, {"m3u8": "https://videojccdn.wzj9.com:8091/20200403/l7f21Ni0/index.m3u8", "img": "https://img2.minqingguancha.com:8099/z-t-img/HEYZO-0475.jpg", "title": "HEYZO-0475不伦的性癖现场撮影"}, {"m3u8": "https://videojccdn.wzj9.com:8091/20200403/4gGHW0eA/index.m3u8", "img": "https://img2.minqingguancha.com:8099/z-t-img/HEYZO-0476.jpg", "title": "HEYZO-0476迷人的人体裸图"}, {"m3u8": "https://videojccdn.wzj9.com:8091/20200403/jKg7wcnU/index.m3u8", "img": "https://img2.minqingguancha.com:8099/z-t-img/HEYZO-0477.jpg", "title": "HEYZO-0477素人妻的浣肠忘我实践"}, {"m3u8": "https://videojccdn.wzj9.com:8091/20200403/4buUfX1Q/index.m3u8", "img": "https://img2.minqingguancha.com:8099/z-t-img/HEYZO-0478.jpg", "title": "HEYZO-0478未体験的淫语快楽"}, {"m3u8": "https://videojccdn.wzj9.com:8091/20200403/IHNJHCFq/index.m3u8", "img": "https://img2.minqingguancha.com:8099/z-t-img/HEYZO-0480.jpg", "title": "HEYZO-0480300人斩的AV女优素顔"}, {"m3u8": "https://videojccdn.wzj9.com:8091/20200403/iU75G0sw/index.m3u8", "img": "https://img2.minqingguancha.com:8099/z-t-img/HEYZO-0481.jpg", "title": "HEYZO-0481诱骗禁断的拘束"}, {"m3u8": "https://videojccdn.wzj9.com:8091/20200403/kfPdg66J/index.m3u8", "img": "https://img2.minqingguancha.com:8099/z-t-img/HEYZO-0482.jpg", "title": "HEYZO-0482职业OL女的交尾"}, {"m3u8": "https://videojccdn.wzj9.com:8091/20200403/ePZuZSB1/index.m3u8", "img": "https://img2.minqingguancha.com:8099/z-t-img/HEYZO-0483.jpg", "title": "HEYZO-0483淫痴性舒适的权限"}, {"m3u8": "https://videozm.whqhyg.com:8091/20200510/tHnAxgkA/index.m3u8", "img": "https://jc.8f23aa8.com/z-t-img/SDNM-237.jpg", "title": "SDNM-237忙于工作育儿的人妻神田知美"}, {"m3u8": "https://videozm.whqhyg.com:8091/20200510/7RzYhZWX/index.m3u8", "img": "https://jc.8f23aa8.com/z-t-img/SDDE-574.jpg", "title": "SDDE-574男装纽约分店穿西服的女店员口交吞精山井铃"}, {"m3u8": "https://videozm.whqhyg.com:8091/20200510/Xv5emlSz/index.m3u8", "img": "https://jc.8f23aa8.com/z-t-img/RBD-497.jpg", "title": "RBD-497困在牢笼内的便利店人妻们"}, {"m3u8": "https://videozm.whqhyg.com:8091/20200510/XX7OQZED/index.m3u8", "img": "https://jc.8f23aa8.com/z-t-img/PRED-237.jpg", "title": "PRED-237社员旅行中只有两个人的办公室"}, {"m3u8": "https://videozm.whqhyg.com:8091/20200510/JBsPl49M/index.m3u8", "img": "https://jc.8f23aa8.com/z-t-img/PRED-233.jpg", "title": "PRED-233美女嫂子山岸逢花的大屁股太骚了"}, {"m3u8": "https://videojccdn.wzj9.com:8091/20200403/zB8pr45B/index.m3u8", "img": "https://img2.minqingguancha.com:8099/z-t-img/HEYZO-0484.jpg", "title": "HEYZO-0484美白正统派美女的快感"}, {"m3u8": "https://videojccdn.wzj9.com:8091/20200403/UDo5RDoa/index.m3u8", "img": "https://img2.minqingguancha.com:8099/z-t-img/HEYZO-0485.jpg", "title": "HEYZO-0485恋人気分大兴奋"}, {"m3u8": "https://videojccdn.wzj9.com:8091/20200403/lR3RkxMp/index.m3u8", "img": "https://img2.minqingguancha.com:8099/z-t-img/HEYZO-0486.jpg", "title": "HEYZO-0486绍介所连続中出性欲女"}, {"m3u8": "https://videojccdn.wzj9.com:8091/20200403/HRfzvvXb/index.m3u8", "img": "https://img2.minqingguancha.com:8099/z-t-img/HEYZO-0487.jpg", "title": "HEYZO-0487AV撮影现场女性乱交"}, {"m3u8": "https://videojccdn.wzj9.com:8091/20200403/m10eQnsR/index.m3u8", "img": "https://img2.minqingguancha.com:8099/z-t-img/HEYZO-0488.jpg", "title": "HEYZO-0488在性爱夜圣诞节的女孩"}]