[{"m3u8": "https://video.feimanzb.com:8091/20171116/IPZ-669-C/550kb/hls/index.m3u8", "img": "https://img.gjtjjp.com/2017-11/IPZ-669-C.jpg", "title": "IPZ-669 虚拟傲娇女友 全篇主観！你跟まゆ的性交的日子！ 希美まゆ"}, {"m3u8": "https://video.feimanzb.com:8091/20171120/MDSC-006-C/550kb/hls/index.m3u8", "img": "https://img.gjtjjp.com/2017-11/MDSC-006-C.jpg", "title": "MDSC-006 淫荡性爱幻想 爱液潺潺的娇躯被侵犯，就在自己的卧室里！荻野舞"}, {"m3u8": "https://video.feimanzb.com:8091/20171120/MDB-703-C/550kb/hls/index.m3u8", "img": "https://img.gjtjjp.com/2017-11/MDB-703-C.jpg", "title": "MDB-703 晒黑女大学生3人组和不受欢迎的巨根的我意外的尽情性交两天一夜旅行 逢沢るる 森はるら 三原ほのか"}, {"m3u8": "https://video.feimanzb.com:8091/20171120/MDB-673-C/550kb/hls/index.m3u8", "img": "https://img.gjtjjp.com/2017-11/MDB-673-C.jpg", "title": "MDB-673 超高级巨乳秘书 森はるら 仓木志乃 甘良しずく 葵千惠"}, {"m3u8": "https://video.feimanzb.com:8091/20171120/MDB-665-C/550kb/hls/index.m3u8", "img": "https://img.gjtjjp.com/2017-11/MDB-665-C.jpg", "title": "MDB-665 掠夺人妻竞拍 渚うるみ 大槻ひびき 北川エリカ 阿部乃みく"}, {"m3u8": "https://video.feimanzb.com:8091/20171120/MDTM-081-C/550kb/hls/index.m3u8", "img": "https://img.gjtjjp.com/2017-11/MDTM-081-C.jpg", "title": "MDTM-081 处女丧失 美少女偶像研究生中出床上营业 みお「为了实现梦想我什幺都干…」"}, {"m3u8": "https://video.feimanzb.com:8091/20171120/MDTM-075-C/550kb/hls/index.m3u8", "img": "https://img.gjtjjp.com/2017-11/MDTM-075-C.jpg", "title": "MDTM-075 放学后美少女回春治疗院 るる"}, {"m3u8": "https://video.feimanzb.com:8091/20171120/MDTM-074-C/550kb/hls/index.m3u8", "img": "https://img.gjtjjp.com/2017-11/MDTM-074-C.jpg", "title": "MDTM-074 因为害羞而不敢跟妈妈说买胸罩…突降大雨让发育中的小胸透出来的少女 东京都板桥区在住 あいり（1●歳）"}, {"m3u8": "https://video.feimanzb.com:8091/20171120/MDTM-072-C/550kb/hls/index.m3u8", "img": "https://img.gjtjjp.com/2017-11/MDTM-072-C.jpg", "title": "MDTM-072 想成为偶像的土气眼镜娘 社长我什幺都做请别抛弃我… 149cm久我かのん"}, {"m3u8": "https://video.feimanzb.com:8091/20171120/MDTM-071-C/550kb/hls/index.m3u8", "img": "https://img.gjtjjp.com/2017-11/MDTM-071-C.jpg", "title": "MDTM-071 让任何人中出的国宝级飞机杯美少女 まい"}, {"m3u8": "https://video.feimanzb.com:8091/20171116/IPZ-650-C/550kb/hls/index.m3u8", "img": "https://img.gjtjjp.com/2017-11/IPZ-650-C.jpg", "title": "IPZ-650 早起拍摄的受虐激情！铁腕女上司被性侵！希志あいの"}, {"m3u8": "https://video.feimanzb.com:8091/20171116/IPZ-646-C/550kb/hls/index.m3u8", "img": "https://img.gjtjjp.com/2017-11/IPZ-646-C.jpg", "title": "IPZ-646 与应召女的性爱激情 最诱人的素人挑逗"}, {"m3u8": "https://video.feimanzb.com:8091/20171116/IPZ-645-C/550kb/hls/index.m3u8", "img": "https://img.gjtjjp.com/2017-11/IPZ-645-C.jpg", "title": "IPZ-645 爆乳女教师的独特授课 涩谷果歩"}, {"m3u8": "https://video.feimanzb.com:8091/20171116/IPZ-644-C/550kb/hls/index.m3u8", "img": "https://img.gjtjjp.com/2017-11/IPZ-644-C.jpg", "title": "IPZ-644 穿超短裙的私塾教师 美腿教师的诱惑 希岛あいり"}, {"m3u8": "https://ginocdn.bybzj.com:8092/zimu/20170730/EGN7KLO334/1/hls/index.m3u8", "img": "https://jc.8f23aa8.com/2017-5/PS/LOVE-334.jpg", "title": "LOVE-334 唯一的興趣就是幹炮爽翻天 市原由芽高清（中文字幕）"}, {"m3u8": "https://video.feimanzb.com:8091/20171116/IPZ-662-C/550kb/hls/index.m3u8", "img": "https://img.gjtjjp.com/2017-11/IPZ-662-C.jpg", "title": "IPZ-662 酒吧店员的挑逗刺激 希岛あいり"}, {"m3u8": "https://video.feimanzb.com:8091/20171116/IPZ-659-C/550kb/hls/index.m3u8", "img": "https://img.gjtjjp.com/2017-11/IPZ-659-C.jpg", "title": "IPZ-659 瞒着男友，兼职按摩女 希崎ジェシカ"}, {"m3u8": "https://video.feimanzb.com:8091/20171116/IPZ-658-C/550kb/hls/index.m3u8", "img": "https://img.gjtjjp.com/2017-11/IPZ-658-C.jpg", "title": "IPZ-658 篮球部的女经纪人沦为性爱玩具 天海つばさ"}, {"m3u8": "https://video.feimanzb.com:8091/20171116/IPZ-656-C/550kb/hls/index.m3u8", "img": "https://img.gjtjjp.com/2017-11/IPZ-656-C.jpg", "title": "IPZ-656 一位普通的姑娘被色狼侵犯，情欲被彻底激发出来！中村梨乃"}, {"m3u8": "https://ginocdn.bybzj.com:8092/zimu/20170730/GW3RJP007/1/hls/index.m3u8", "img": "https://jc.8f23aa8.com/2017-5/PS/NAMG-007.jpg", "title": "NAMG-007 純真x白嫩柔肌x未開發美少女 19歲（中文字幕）"}, {"m3u8": "https://video.feimanzb.com:8091/20171120/MEYD-072-C/550kb/hls/index.m3u8", "img": "https://img.gjtjjp.com/2017-11/MEYD-072-C.jpg", "title": "MEYD-072 美熟女的专属性爱激情 めぐり"}, {"m3u8": "https://video.feimanzb.com:8091/20171120/MEYD-042-C/550kb/hls/index.m3u8", "img": "https://img.gjtjjp.com/2017-11/MEYD-042-C.jpg", "title": "MEYD-042 那炎热的夜晚 本城小百合"}, {"m3u8": "https://video.feimanzb.com:8091/20171120/MDTM-148-C/550kb/hls/index.m3u8", "img": "https://img.gjtjjp.com/2017-11/MDTM-148-C.jpg", "title": "MDTM-148 能无套中出的美少女妈妈应招女 阿部乃みく"}, {"m3u8": "https://video.feimanzb.com:8091/20171120/MDTM-084-C/550kb/hls/index.m3u8", "img": "https://img.gjtjjp.com/2017-11/MDTM-084-C.jpg", "title": "MDTM-084 白虎小穴大汗淋漓女高中生 土屋あさみ 美少女性欲全开的激烈中出性交"}, {"m3u8": "https://video.feimanzb.com:8091/20171120/MEYD-090-C/550kb/hls/index.m3u8", "img": "https://img.gjtjjp.com/2017-11/MEYD-090-C.jpg", "title": "MEYD-090 丈夫不在家，人妻被公公强奸 筱田あゆみ"}, {"m3u8": "https://video.feimanzb.com:8091/20171120/MEYD-089-C/550kb/hls/index.m3u8", "img": "https://img.gjtjjp.com/2017-11/MEYD-089-C.jpg", "title": "MEYD-089 被丈夫弟弟侵犯的嫂子 三浦恵理子"}, {"m3u8": "https://video.feimanzb.com:8091/20171120/MEYD-088-C/550kb/hls/index.m3u8", "img": "https://img.gjtjjp.com/2017-11/MEYD-088-C.jpg", "title": "MEYD-088 丈夫的兴趣是让妻子穿上孩子衣服 38岁人妻神谷秋妃"}, {"m3u8": "https://video.feimanzb.com:8091/20171120/MEYD-086-C/550kb/hls/index.m3u8", "img": "https://img.gjtjjp.com/2017-11/MEYD-086-C.jpg", "title": "MEYD-086 我不断被丈夫的上司侵犯 吉浦みさと"}, {"m3u8": "https://video.feimanzb.com:8091/20171120/MEYD-085-C/550kb/hls/index.m3u8", "img": "https://img.gjtjjp.com/2017-11/MEYD-085-C.jpg", "title": "MEYD-085 银座的一家高级按摩店！本城小百合"}, {"m3u8": "https://video.feimanzb.com:8091/20171120/MEYD-084-C/550kb/hls/index.m3u8", "img": "https://img.gjtjjp.com/2017-11/MEYD-084-C.jpg", "title": "MEYD-084 遭遇继子的鬼畜性侵 东凛"}, {"m3u8": "https://ginocdn.bybzj.com:8092/zimu/20170730/EN5HKJBR162/1/hls/index.m3u8", "img": "https://jc.8f23aa8.com/2017-5/PS/SQTE-162.jpg", "title": "SQTE-162 不可以談淫亂的戀愛嗎？短髮可愛美少女的性愛情事（中文字幕）"}, {"m3u8": "https://video.feimanzb.com:8091/20171120/MEYD-082-C/550kb/hls/index.m3u8", "img": "https://img.gjtjjp.com/2017-11/MEYD-082-C.jpg", "title": "MEYD-082 露出调教，人妻的诱惑 吉浦みさと"}, {"m3u8": "https://video.feimanzb.com:8091/20171120/MEYD-079-C/550kb/hls/index.m3u8", "img": "https://img.gjtjjp.com/2017-11/MEYD-079-C.jpg", "title": "MEYD-079 被监禁在家里的人妻 川上ゆう"}, {"m3u8": "https://video.feimanzb.com:8091/20171120/MEYD-078-C/550kb/hls/index.m3u8", "img": "https://img.gjtjjp.com/2017-11/MEYD-078-C.jpg", "title": "MEYD-078 朋友的母亲 一直被儿子的朋友侵犯，高潮迭起的爱爱 秋山静香"}, {"m3u8": "https://ginocdn.bybzj.com:8092/zimu/20170730/ERW3MBF013/1/hls/index.m3u8", "img": "https://jc.8f23aa8.com/2017-5/PS/MUDR-013.jpg", "title": "MUDR-013 向癡漢說不 完全版 希美真由（中文字幕）"}, {"m3u8": "https://video.feimanzb.com:8091/20171120/MEYD-073-C/550kb/hls/index.m3u8", "img": "https://img.gjtjjp.com/2017-11/MEYD-073-C.jpg", "title": "MEYD-073 虽然相信妻子，但是···东凛"}]