[{"m3u8": "https://videocdn2.quweikm.com:8091/20181201/GJK3OTR068/index.m3u8", "img": "https://img2.minqingguancha.com:8099/2018-12/GJK3OTR068.jpg", "title": "GETS-068 喜欢泡温泉的人妻在温泉中被埋伏的癡汉袭击、乱交了…"}, {"m3u8": "https://videocdn2.quweikm.com:8091/20181201/JBIK3ELW521/index.m3u8", "img": "https://img2.minqingguancha.com:8099/2018-12/JBIK3ELW521.jpg", "title": "JUY-521 比全裸更羞耻 穿着超短下装的人妻 加濑佳奈子"}, {"m3u8": "https://videocdn2.quweikm.com:8091/20181201/HYIL5OR559/index.m3u8", "img": "https://img2.minqingguancha.com:8099/2018-12/HYIL5OR559.jpg", "title": "HND-559 女友妹妹因太爱我了于是偷偷与她受孕性交 岩濑理名"}, {"m3u8": "https://videocdn2.quweikm.com:8091/20181201/IKIBE5RW176/index.m3u8", "img": "https://img2.minqingguancha.com:8099/2018-12/IKIBE5RW176.jpg", "title": "IPX-176 不穿内裤不穿胸衣只穿透明装 偶像的神对应 隔着魔术镜诱惑！发情客人们暴走！"}, {"m3u8": "https://videocdn2.quweikm.com:8091/20181201/IWK2LEF167/index.m3u8", "img": "https://img2.minqingguancha.com:8099/2018-12/IWK2LEF167.jpg", "title": "IPX-167 欢迎来到超高级变态泡泡浴 由完美的美女们带领肉棒前往梦幻3轮车性爱天堂特别服务"}, {"m3u8": "https://videocdn2.quweikm.com:8091/20181201/HQI8EFS00047/index.m3u8", "img": "https://img2.minqingguancha.com:8099/2018-12/HQI8EFS00047.jpg", "title": "HOMA-00047 人妻的约砲日记 南亚矢"}, {"m3u8": "https://videocdn2.quweikm.com:8091/20181201/HWK3IOGR418/index.m3u8", "img": "https://img2.minqingguancha.com:8099/2018-12/HWK3IOGR418.jpg", "title": "HBAD-418 买豪宅却缴不出贷款 只好欠债肉偿 蓝川广"}, {"m3u8": "https://videocdn2.quweikm.com:8091/20181201/HKL6BER056/index.m3u8", "img": "https://img2.minqingguancha.com:8099/2018-12/HKL6BER056.jpg", "title": "HQIS-056 亨利冢本原作 血亲性交 禁断的性爱 兄妹?落入肉慾的兄妹二人/比起丈夫还是父亲更厉害/继父和好色女儿/父亲的腰技"}, {"m3u8": "https://videocdn2.quweikm.com:8091/20181201/HQK2FEL119/index.m3u8", "img": "https://img2.minqingguancha.com:8099/2018-12/HQK2FEL119.jpg", "title": "HTMS-119 ヘンリー冢本 让男人把持不住的超大乳房"}, {"m3u8": "https://videocdn2.quweikm.com:8091/20181201/HWKIE6FRL538/index.m3u8", "img": "https://img2.minqingguancha.com:8099/2018-12/HWKIE6FRL538.jpg", "title": "HND-538 沉浸在爱和快乐之中最棒的内射性爱 美谷朱里"}, {"m3u8": "https://videocdn2.quweikm.com:8091/20181201/HWB8VKLO485/index.m3u8", "img": "https://img2.minqingguancha.com:8099/2018-12/HWB8VKLO485.jpg", "title": "HND-485 绝对会怀孕的！不戴套内射到怀孕！ 美谷朱里"}, {"m3u8": "https://videocdn2.quweikm.com:8091/20181201/HKIRL6WQ21305/index.m3u8", "img": "https://img2.minqingguancha.com:8099/2018-12/HKIRL6WQ21305.jpg", "title": "HODV-21305 新人 超美九头身 星乃栞 美腿纤瘦女大学生AV出道！！"}, {"m3u8": "https://videocdn2.quweikm.com:8091/20181201/HQE4FIA534/index.m3u8", "img": "https://img2.minqingguancha.com:8099/2018-12/HQE4FIA534.jpg", "title": "HND-534 高潮堕落在从背后侵入到小穴深处的肉棒里，危险日让人怀孕背后痴汉 星奈爱"}, {"m3u8": "https://videocdn2.quweikm.com:8091/20181201/HWE0JKGE465/index.m3u8", "img": "https://img2.minqingguancha.com:8099/2018-12/HWE0JKGE465.jpg", "title": "HUNTA-465 我和义姐练习做爱…"}, {"m3u8": "https://videocdn2.quweikm.com:8091/20181201/HKL0BRW516/index.m3u8", "img": "https://img2.minqingguancha.com:8099/2018-12/HKL0BRW516.jpg", "title": "HND-516 寻找情人，只体验一夜情的她跟大叔内射性交 彩岸麻衣"}, {"m3u8": "https://videocdn2.quweikm.com:8091/20181201/HTK3IHLF466/index.m3u8", "img": "https://img2.minqingguancha.com:8099/2018-12/HTK3IHLF466.jpg", "title": "HUNTA-466 在合宿中的女子体操社只能靠我的老二喘口气！！"}, {"m3u8": "https://videocdn2.quweikm.com:8091/20181201/HKI7BWR138/index.m3u8", "img": "https://img2.minqingguancha.com:8099/2018-12/HKI7BWR138.jpg", "title": "HDKA-138 全裸主妇 住在町田市 高岛优香 (29)"}, {"m3u8": "https://videocdn2.quweikm.com:8091/20181201/HLN1ET503/index.m3u8", "img": "https://img2.minqingguancha.com:8099/2018-12/HLN1ET503.jpg", "title": "HND-503 哥哥为了满足妹妹的变态慾望让她出演av！"}, {"m3u8": "https://videocdn2.quweikm.com:8091/20181201/HVW1ALS494-A/index.m3u8", "img": "https://img2.minqingguancha.com:8099/2018-12/HVW1ALS494-A.jpg", "title": "HUNTA-494 想交女友！搬进男人仅有我一人分租套房 2"}, {"m3u8": "https://videocdn2.quweikm.com:8091/20181201/HKIE3RLW46-A/index.m3u8", "img": "https://img2.minqingguancha.com:8099/2018-12/HKIE3RLW46-A.jpg", "title": "HUNTA-461 超可爱最近又开始发育的女高中生妹妹让我心痒痒！！"}, {"m3u8": "https://videocdn2.quweikm.com:8091/20181201/HQ7KEFL570/index.m3u8", "img": "https://img2.minqingguancha.com:8099/2018-12/HQ7KEFL570.jpg", "title": "HND-570 初次的内射 夏原唯"}, {"m3u8": "https://videocdn.hndtl.com:8091/20181120/WANZ-788c/index.m3u8", "img": "https://jc.8f23aa8.com/2018-11/PS/WANZ-788.jpg", "title": "WANZ-788c-251発の媚薬濃縮精液註入 佐々木あき"}, {"m3u8": "https://videocdn.hndtl.com:8091/20181120/WANZ-789c/index.m3u8", "img": "https://jc.8f23aa8.com/2018-11/PS/WANZ-789.jpg", "title": "WANZ-789c-朝はすっご媚薬..."}, {"m3u8": "https://video2.dnsoy.com:8091/9720180501/ABP-335c/650kb/hls/index.m3u8", "img": "https://bbs.sezytp.com/pic/uploadimg/2018-4/PS/ABP-335.jpg", "title": "ABP-335cABP-335 女上位荡妇 桐嶋りの"}, {"m3u8": "https://video2.dnsoy.com:8091/9720180501/ABP-340c/650kb/hls/index.m3u8", "img": "https://bbs.sezytp.com/pic/uploadimg/2018-4/PS/ABP-340.jpg", "title": "ABP-340cABP-340 絶頂乳液 冬月かえで"}, {"m3u8": "https://video2.dnsoy.com:8091/9720180501/ABP-342c/650kb/hls/index.m3u8", "img": "https://bbs.sezytp.com/pic/uploadimg/2018-4/PS/ABP-342.jpg", "title": "ABP-342cABP-342 夏祭美少女 長谷川るい"}, {"m3u8": "https://videocdn2.quweikm.com:8091/20181201/IKB8RLW191/index.m3u8", "img": "https://img2.minqingguancha.com:8099/2018-12/IKB8RLW191.jpg", "title": "IPX-191 丑闻 搭讪带回家的『明里紬』被偷拍录影发售AV！ 解禁！！私人性爱 难以攻破的防弹女优被说服做爱始末！！"}, {"m3u8": "https://videocdn2.quweikm.com:8091/20181201/IQK0LOFE03/index.m3u8", "img": "https://img2.minqingguancha.com:8099/2018-12/IQK0LOFE03.jpg", "title": "IWAN-03 淫乱太太的妖豔情趣内衣性交 水野优香"}, {"m3u8": "https://videocdn2.quweikm.com:8091/20181201/JBRD6ZA461/index.m3u8", "img": "https://img2.minqingguancha.com:8099/2018-12/JBRD6ZA461.jpg", "title": "JUY-461 嫂子的柔顺肌肤 加濑佳奈子"}, {"m3u8": "https://videocdn2.quweikm.com:8091/20181201/IKBR9WW106/index.m3u8", "img": "https://img2.minqingguancha.com:8099/2018-12/IKBR9WW106.jpg", "title": "IPX-106 穿着各种运动服激烈抽插！小麦色的美丽肌肤！E罩杯丰满色情身材！×精选好撸运动服！×完美拍摄角度！植村惠名"}, {"m3u8": "https://videocdn2.quweikm.com:8091/20181201/IEFL8OW159/index.m3u8", "img": "https://img2.minqingguancha.com:8099/2018-12/IEFL8OW159.jpg", "title": "IPX-159 堕落与公公性交快感的完美嫩妻… 相泽南"}, {"m3u8": "https://videocdn2.quweikm.com:8091/20181201/IKLO0BRW150/index.m3u8", "img": "https://img2.minqingguancha.com:8099/2018-12/IKLO0BRW150.jpg", "title": "IPX-150 在职场散发费洛蒙 工作的癡女大姐姐用散发着味道的丝袜美腿诱惑人做爱 有原步美"}, {"m3u8": "https://videocdn2.quweikm.com:8091/20181201/JBR3LW548/index.m3u8", "img": "https://img2.minqingguancha.com:8099/2018-12/JBR3LW548.jpg", "title": "JUY-548 丈夫去世，服丧期间，寡妇被丈夫的学生们侵犯了 久保今日子"}, {"m3u8": "https://videocdn2.quweikm.com:8091/20181201/IKB01FWQ185/index.m3u8", "img": "https://img2.minqingguancha.com:8099/2018-12/IKB01FWQ185.jpg", "title": "IPX-185 护士因为太忙一个月没有发洩慾望结果性慾爆发了 从深夜到黎明疯狂10连射！！ 西宫梦"}, {"m3u8": "https://videocdn2.quweikm.com:8091/20181201/IKW2ETR136/index.m3u8", "img": "https://img2.minqingguancha.com:8099/2018-12/IKW2ETR136.jpg", "title": "IPX-136 突击！！单体女优神咲诗织潜入传说中的卖淫店体验报导！！性爱沙龙!M洗体！！洗体按摩！！张大小穴及肉体潜入採访性爱酒吧"}, {"m3u8": "https://videocdn2.quweikm.com:8091/20181201/IBKI0RW896/index.m3u8", "img": "https://img2.minqingguancha.com:8099/2018-12/IBKI0RW896.jpg", "title": "IENE-896 一之瀬梓 从早到晚中出干炮 32"}]