[{"m3u8": "https://videocdn.dlyilian.com:8091/20190331/JK6JYUC373/index.m3u8", "img": "https://img2.minqingguancha.com:8099/2019-3/JK6JYUC373.jpg", "title": "JKSR-373 真正内射！颜射！搭讪五十多岁 in 品川"}, {"m3u8": "https://videocdn.dlyilian.com:8091/20190105/hd_tokyo_hot-k1210/index.m3u8", "img": "https://img2.minqingguancha.com:8099/2019-1/hd_tokyo_hot-k1210.jpg", "title": "Tokyo_Hot-k1210 餌食牝 若林江実"}, {"m3u8": "https://videocdn.dlyilian.com:8091/20190331/JR4UJKC826/index.m3u8", "img": "https://img2.minqingguancha.com:8099/2019-3/JR4UJKC826.jpg", "title": "JRZD-826 人妻初拍纪录片 槙原彩"}, {"m3u8": "https://videocdn.dlyilian.com:8091/20190331/JU2TJUD726/index.m3u8", "img": "https://img2.minqingguancha.com:8099/2019-3/JU2TJUD726.jpg", "title": "JUY-726 出差后住旅馆没想到居然和喜欢的美女上司住一间 佐佐木明希"}, {"m3u8": "https://videocdn.dlyilian.com:8091/20190331/JU7KTUSD675/index.m3u8", "img": "https://img2.minqingguancha.com:8099/2019-3/JU7KTUSD675.jpg", "title": "JUY-675 原地方播音员 内射解禁！！高学历人妻被低学历的精子注入之后会变笨蛋 。 三田真利江"}, {"m3u8": "https://videocdn.dlyilian.com:8091/20190331/JU4YUIF708/index.m3u8", "img": "https://img2.minqingguancha.com:8099/2019-3/JU4YUIF708.jpg", "title": "JUY-708 人妻力满载的无敌美熟女！！ 人妻沉迷在背德的性感美容沙龙中 望月留美"}, {"m3u8": "https://videocdn.dlyilian.com:8091/20190331/JR1WRJT838/index.m3u8", "img": "https://img2.minqingguancha.com:8099/2019-3/JR1WRJT838.jpg", "title": "JRZD-838 初次拍摄人妻纪录片 仲山由纪江"}, {"m3u8": "https://videocdn.dlyilian.com:8091/20190331/JU2HKCS994/index.m3u8", "img": "https://img2.minqingguancha.com:8099/2019-3/JU2HKCS994.jpg", "title": "JUFD-994 超让人不爽的美女秘书成了我肉棒的绝对服从人肉飞机杯 本田岬"}, {"m3u8": "https://videocdn.dlyilian.com:8091/20190331/JU6OIGF099/index.m3u8", "img": "https://img2.minqingguancha.com:8099/2019-3/JU6OIGF099.jpg", "title": "JUTA-099 极品！四十岁夫人初次拍摄AV 生驹堇"}, {"m3u8": "https://videocdn.dlyilian.com:8091/20190331/JR2YJIV853/index.m3u8", "img": "https://img2.minqingguancha.com:8099/2019-3/JR2YJIV853.jpg", "title": "JRZD-853 初次拍摄新人纪录片 东沙雪"}, {"m3u8": "https://videocdn.dlyilian.com:8091/20190331/JU4UYG676/index.m3u8", "img": "https://img2.minqingguancha.com:8099/2019-3/JU4UYG676.jpg", "title": "JUY-676 暴风雨 喜欢的房屋仲介小姐和我独处的夜晚 水戸加奈"}, {"m3u8": "https://videocdn.dlyilian.com:8091/20190331/JU1RYUK659/index.m3u8", "img": "https://img2.minqingguancha.com:8099/2019-3/JU1RYUK659.jpg", "title": "JUY-659 「接着等你回来再继续？」被阿姨吊胃口，成为大人的3日 三浦恵理子"}, {"m3u8": "https://videocdn.dlyilian.com:8091/20190331/JU1HTNK668/index.m3u8", "img": "https://img2.minqingguancha.com:8099/2019-3/JU1HTNK668.jpg", "title": "JUY-668 我被隔壁太太用各种方法管理我的射精的一星期 西野翔"}, {"m3u8": "https://videocdn.dlyilian.com:8091/20190331/IP9ILWD246/index.m3u8", "img": "https://img2.minqingguancha.com:8099/2019-3/IP9ILWD246.jpg", "title": "IPX-246 「我高潮了！所以不要动了！」高潮后被连续追击抽插 备受期待的人气系列参战！ 相泽南"}, {"m3u8": "https://videocdn.dlyilian.com:8091/20190331/JK6JYFSA374/index.m3u8", "img": "https://img2.minqingguancha.com:8099/2019-3/JK6JYFSA374.jpg", "title": "JKSR-374 乡下的偶像 没想到竟然出演AV了！！F杯淳朴女孩被内射！！ しおり小姐F杯"}, {"m3u8": "https://videocdn.dlyilian.com:8091/20190331/JQUE5IW636/index.m3u8", "img": "https://img2.minqingguancha.com:8099/2019-3/JQUE5IW636.jpg", "title": "JUY-636 妻子被别人拥抱着...。 赤木碧"}, {"m3u8": "https://videocdn.dlyilian.com:8091/20190331/IP4JTUD233/index.m3u8", "img": "https://img2.minqingguancha.com:8099/2019-3/IP4JTUD233.jpg", "title": "HD IPX-233 癡女后宫住院楼～被几个护士推倒的你～有码高清"}, {"m3u8": "https://videocdn.dlyilian.com:8091/20190331/JQDF9HV641/index.m3u8", "img": "https://img2.minqingguancha.com:8099/2019-3/JQDF9HV641.jpg", "title": "JUY-641 从背后将我弄得意乱情迷吧…。 ~满足人妻被侵犯愿望的背后为性交~ 宝生莉莉"}, {"m3u8": "https://videocdn.dlyilian.com:8091/20190331/IP7KUTDS224/index.m3u8", "img": "https://img2.minqingguancha.com:8099/2019-3/IP7KUTDS224.jpg", "title": "HD IPX-224 清纯学生的青涩性慾 性慾超强的杏老师的单人授课 日乃原杏有码高清"}, {"m3u8": "https://videocdn.dlyilian.com:8091/20190331/JJ2UYJH128/index.m3u8", "img": "https://img2.minqingguancha.com:8099/2019-3/JJ2UYJH128.jpg", "title": "JJPP-128 偷拍帅哥把熟女带入房间做爱的影片 FANZA限定！ 先行发售特别版！！61"}, {"m3u8": "https://videocdn.dlyilian.com:8091/20190331/IQEG9TRH212/index.m3u8", "img": "https://img2.minqingguancha.com:8099/2019-3/IQEG9TRH212.jpg", "title": "IPX-212 心跳初体验！让我露出欺负我让我高潮吧… 七实理名"}, {"m3u8": "https://videocdn.dlyilian.com:8091/20190331/JQ4ETH553/index.m3u8", "img": "https://img2.minqingguancha.com:8099/2019-3/JQ4ETH553.jpg", "title": "JUY-553 原艺人人妻 麦当娜专属第二期！传说中的女儿男朋友来了…坛惠美"}, {"m3u8": "https://videocdn.dlyilian.com:8091/20190331/KEFE1GR071/index.m3u8", "img": "https://img2.minqingguancha.com:8099/2019-3/KEFE1GR071.jpg", "title": "KRI-071 丈夫不知不觉间！！素人应招人妻 ※擅自当AV卖！！！ 出轨人妻的愿望 3"}, {"m3u8": "https://videocdn.dlyilian.com:8091/20190105/hd_tokyo_hot-k1211/index.m3u8", "img": "https://img2.minqingguancha.com:8099/2019-1/hd_tokyo_hot-k1211.jpg", "title": "Tokyo_Hot-k1211 餌食牝 成田郁美"}, {"m3u8": "https://videocdn.dlyilian.com:8091/20190105/hd_tokyo_hot-k1212/index.m3u8", "img": "https://img2.minqingguancha.com:8099/2019-1/hd_tokyo_hot-k1212.jpg", "title": "Tokyo_Hot-k1212 餌食牝 菅崎雅美"}, {"m3u8": "https://videocdn.dlyilian.com:8091/20190331/JU4TRQWE978/index.m3u8", "img": "https://img2.minqingguancha.com:8099/2019-3/JU4TRQWE978.jpg", "title": "JUFD-978 美女痉挛到不行的追击性交 铃木里美"}, {"m3u8": "https://videocdn.dlyilian.com:8091/20190331/JU8UKRG998/index.m3u8", "img": "https://img2.minqingguancha.com:8099/2019-3/JU8UKRG998.jpg", "title": "JUFD-998 先是撒娇然后突变！说着下流话侵犯我的变态妈妈 小早川怜子"}, {"m3u8": "https://videocdn.dlyilian.com:8091/20190331/JU1HJYFB686/index.m3u8", "img": "https://img2.minqingguancha.com:8099/2019-3/JU1HJYFB686.jpg", "title": "JUY-686 能挤出母乳的三十多岁人妻第二期1 丈夫的下属不断玩弄她敏感的乳头不停的流出奶…上司的妻子西野美幸"}, {"m3u8": "https://videocdn.dlyilian.com:8091/20190331/JU4TYIOF591/index.m3u8", "img": "https://img2.minqingguancha.com:8099/2019-3/JU4TYIOF591.jpg", "title": "JUY-591 寡妇在丈夫的遗照面前被侵犯到高潮。并木塔子"}, {"m3u8": "https://videocdn.dlyilian.com:8091/20190331/JU9KUVB655/index.m3u8", "img": "https://img2.minqingguancha.com:8099/2019-3/JU9KUVB655.jpg", "title": "JUY-655 与附近邻居一大早就猛烈开干 早川瑞希"}, {"m3u8": "https://videocdn.dlyilian.com:8091/20190331/JU8KUTSD656/index.m3u8", "img": "https://img2.minqingguancha.com:8099/2019-3/JU8KUTSD656.jpg", "title": "JUY-656 偷偷帮忙儿子好友破处的母亲 一色桃子"}, {"m3u8": "https://videocdn.dlyilian.com:8091/20190331/JU0JTRDN977/index.m3u8", "img": "https://img2.minqingguancha.com:8099/2019-3/JU0JTRDN977.jpg", "title": "JUFD-977 监禁禁慾到性慾爆发的男人！ 双癡女榨精做爱 美保结衣 宝生莉莉"}, {"m3u8": "https://videocdn.dlyilian.com:8091/20190331/JU3TYQD736/index.m3u8", "img": "https://img2.minqingguancha.com:8099/2019-3/JU3TYQD736.jpg", "title": "JUY-736 如果你喜欢这样的我的话……和年龄差距很大的女领导做爱 一色桃子"}, {"m3u8": "https://videocdn.dlyilian.com:8091/20190331/JU8LIGHF454/index.m3u8", "img": "https://img2.minqingguancha.com:8099/2019-3/JU8LIGHF454.jpg", "title": "HD JUY-454 出门上班及回家都是同方向的附近人妻某天突然接近。 桥本丽香有码高清"}, {"m3u8": "https://videocdn.dlyilian.com:8091/20190331/JU0UAQ669/index.m3u8", "img": "https://img2.minqingguancha.com:8099/2019-3/JU0UAQ669.jpg", "title": "JUY-669 无尽快感 ～俘虏人妻偷情爱抚～ 春香未来"}, {"m3u8": "https://videocdn.dlyilian.com:8091/20190331/JR7UKIF840/index.m3u8", "img": "https://img2.minqingguancha.com:8099/2019-3/JR7UKIF840.jpg", "title": "JRZD-840 初拍五十岁人妻记录片 及川里香子"}]