[{"m3u8": "https://videozm.whqhyg.com:8091/20201109/h20Cmpia/index.m3u8", "img": "https://img2.minqingguancha.com:8099/z-t-img/MDBK-022.jpg", "title": "MDBK-022被裸体美女填满！！永井みひな"}, {"m3u8": "https://videozm.whqhyg.com:8091/20201109/apwWUZNW/index.m3u8", "img": "https://img2.minqingguancha.com:8099/z-t-img/MIAA-058.jpg", "title": "MIAA-058射精也不犯鼓膜继续诱惑低语中年老爸狩猎不拔的贴身新闻姐姐筱田优"}, {"m3u8": "https://videozm.whqhyg.com:8091/20201109/hWE3S5lG/index.m3u8", "img": "https://videozm.whqhyg.com:8091/20201109/hWE3S5lG/index.m3u8", "title": "MIAA-059女朋友交换~同学情侣中出乌贼合学园性活~深田惠美黑崎美香"}, {"m3u8": "https://videozm.whqhyg.com:8091/20201109/2M0HbNnO/index.m3u8", "img": "https://img2.minqingguancha.com:8099/z-t-img/MIAA-060.jpg", "title": "我被告知最喜欢MIAA-060的前女友第一次学会了伊基。星奈爱"}, {"m3u8": "https://videozm.whqhyg.com:8091/20201109/Bw1aM1IN/index.m3u8", "img": "https://img2.minqingguancha.com:8099/z-t-img/MOND-165.jpg", "title": "MOND-165憧憬的女上司和一之濑彩芽"}, {"m3u8": "https://videozm.whqhyg.com:8091/20201109/HIFncxGk/index.m3u8", "img": "https://img2.minqingguancha.com:8099/z-t-img/NHDTB-259.jpg", "title": "NHDTB-259最喜欢的叔叔的让他直接中出的侄女2 森永ぴの"}, {"m3u8": "https://videozm.whqhyg.com:8091/20201109/O2Q6lrOY/index.m3u8", "img": "https://videozm.whqhyg.com:8091/20201109/O2Q6lrOY/index.m3u8", "title": "NTRD-075驯养依赖开坂花恋"}, {"m3u8": "https://videozm.whqhyg.com:8091/20201109/XLuA2SAp/index.m3u8", "img": "https://img2.minqingguancha.com:8099/z-t-img/RCTD-218.jpg", "title": "RCTD-218 BYYYYK Shuta附身番外篇 御坂りあ"}, {"m3u8": "https://videozm.whqhyg.com:8091/20201109/mypCijNL/index.m3u8", "img": "https://img2.minqingguancha.com:8099/z-t-img/RCTD-219.jpg", "title": "RCTD-219魔术米勒号朋友们的女孩共享0波W口交体验"}, {"m3u8": "https://videozm.whqhyg.com:8091/20201109/AGSOJxJu/index.m3u8", "img": "https://img2.minqingguancha.com:8099/z-t-img/SDAM-014.jpg", "title": "SDAM-014[限时情人节爱好者们能不被发现地度过吗 跡美しゅり"}, {"m3u8": "https://videozm.whqhyg.com:8091/20201109/7iQ2qhRP/index.m3u8", "img": "https://img2.minqingguancha.com:8099/z-t-img/SDDE-571.jpg", "title": "SDDE-571射精管理女经理~不能集中精力练习的社员射精控制器/地区冠军！"}, {"m3u8": "https://videozm.whqhyg.com:8091/20201109/To1yT8Og/index.m3u8", "img": "https://img2.minqingguancha.com:8099/z-t-img/SDJS-016.jpg", "title": "SDJS-016 SOD女职员中途入社宣传部第2年绫濑麻衣子中橡胶"}, {"m3u8": "https://videojccdn.wzj9.com:8091/20201117/hvux00001-Part-4/index.m3u8", "img": "https://jc.8f23aa8.com/2020/02/hvux00001.jpg", "title": "HVUX-001 巨乳熟女に大量中出し 愛液まみれで失神寸前！-D"}, {"m3u8": "https://videojccdn.wzj9.com:8091/20201117/hvux00001-Part-3/index.m3u8", "img": "https://jc.8f23aa8.com/2020/02/hvux00001.jpg", "title": "HVUX-001 巨乳熟女に大量中出し 愛液まみれで失神寸前！-C"}, {"m3u8": "https://videojccdn.wzj9.com:8091/20201117/hvux00001-Part-2/index.m3u8", "img": "https://jc.8f23aa8.com/2020/02/hvux00001.jpg", "title": "HVUX-001 巨乳熟女に大量中出し 愛液まみれで失神寸前！-B"}, {"m3u8": "https://videojccdn.wzj9.com:8091/20201117/hvux00001-Part-1/index.m3u8", "img": "https://jc.8f23aa8.com/2020/02/hvux00001.jpg", "title": "HVUX-001 巨乳熟女に大量中出し 愛液まみれで失神寸前！-A"}, {"m3u8": "https://videozm.whqhyg.com:8091/20201110/6u5olbVV/index.m3u8", "img": "https://img2.minqingguancha.com:8099/z-t-img/NPV-023.jpg", "title": "NPV-023搭讪TV×PRESTIGE PREMIUM18大捕鱼！！深田結梨"}, {"m3u8": "https://videozm.whqhyg.com:8091/20201110/0t4pRMJ2/index.m3u8", "img": "https://img2.minqingguancha.com:8099/z-t-img/OKAX-497.jpg", "title": "OKAX-497 15个外行女儿羞愧欲情奇0波鉴赏会4小时小林るな"}, {"m3u8": "https://videozm.whqhyg.com:8091/20201110/jFBSWc2N/index.m3u8", "img": "https://img2.minqingguancha.com:8099/z-t-img/OKAX-498.jpg", "title": "OKAX-498宣扬外行女儿到陷害为止"}, {"m3u8": "https://videozm.whqhyg.com:8091/20201110/6u1P9bly/index.m3u8", "img": "https://img2.minqingguancha.com:8099/z-t-img/OKAX-500.jpg", "title": "OKAX-500无力还债的人妻潜入被质押的现场！"}, {"m3u8": "https://videozm.whqhyg.com:8091/20201110/rmxS5hYm/index.m3u8", "img": "https://img2.minqingguancha.com:8099/z-t-img/SCOP-621.jpg", "title": "目睹SCOP-621 被拍摄现场的气氛所吞噬性爱的女人们"}, {"m3u8": "https://videozm.whqhyg.com:8091/20201110/2hrjr6y2/index.m3u8", "img": "https://img2.minqingguancha.com:8099/z-t-img/SCPX-352.jpg", "title": "SCPX-352某著名视频发布单元拍摄的影像太过色情 優月まりな"}, {"m3u8": "https://videozm.whqhyg.com:8091/20201110/JTN1Ig0Y/index.m3u8", "img": "https://img2.minqingguancha.com:8099/z-t-img/SGA-127.jpg", "title": "SGA-127最好的情妇和最好的中出性交。 巨乳美女 奈槻れいら"}, {"m3u8": "https://videozm.whqhyg.com:8091/20201110/vOmspVtP/index.m3u8", "img": "https://img2.minqingguancha.com:8099/z-t-img/SUPA-449.jpg", "title": "SUPA-449在传闻中的匹配应用程序中遇到了一个高概率的暴乳N"}, {"m3u8": "https://videozm.whqhyg.com:8091/20201111/BmiWRWGr/index.m3u8", "img": "https://img2.minqingguancha.com:8099/z-t-img/SUPA-451.jpg", "title": "SUPA-451超绝身材极品美女中出SEX50人4小时BEST2"}, {"m3u8": "https://videozm.whqhyg.com:8091/20201111/2Y0tZh09/index.m3u8", "img": "https://img2.minqingguancha.com:8099/z-t-img/VENU-863.jpg", "title": "VENU-863亲属相奸漂亮的姨妈岬小豆"}, {"m3u8": "https://videozm.whqhyg.com:8091/20201111/LVr0qTsA/index.m3u8", "img": "https://img2.minqingguancha.com:8099/z-t-img/VENU-864.jpg", "title": "VENU-864父亲出门2秒做爱母亲和儿子音羽文子"}, {"m3u8": "https://videozm.whqhyg.com:8091/20201111/Qn6ddJfE/index.m3u8", "img": "https://videozm.whqhyg.com:8091/20201111/Qn6ddJfE/index.m3u8", "title": "VENU-865退休后成为时间的德斯基继父的媳妇水野优香。"}, {"m3u8": "https://videozm.whqhyg.com:8091/20201111/n6V4JcXO/index.m3u8", "img": "https://img2.minqingguancha.com:8099/z-t-img/WANZ-852.jpg", "title": "WANZ-852家庭跟踪狂孕育×普JULIA"}, {"m3u8": "https://videozm.whqhyg.com:8091/20201111/Nkv70JNG/index.m3u8", "img": "https://img2.minqingguancha.com:8099/z-t-img/WANZ-853.jpg", "title": "WANZ-853被讨厌的继父熬夜…。有坂深雪"}, {"m3u8": "https://videozm.whqhyg.com:8091/20201111/q1DLUujM/index.m3u8", "img": "https://img2.minqingguancha.com:8099/z-t-img/XRW-674.jpg", "title": "XRW-674被一个陌生的男人抱在丈夫的债务…。音海里奈/川崎亚里沙"}, {"m3u8": "https://videozm.whqhyg.com:8091/20201111/hBOM2ov2/index.m3u8", "img": "https://img2.minqingguancha.com:8099/z-t-img/YAL-128.jpg", "title": "YAL-128友女友的睡脸默默地卖了大泽KASMI"}, {"m3u8": "https://videozm.whqhyg.com:8091/20201111/YMEqeLna/index.m3u8", "img": "https://img2.minqingguancha.com:8099/z-t-img/YST-187.jpg", "title": "YST-187我被恐吓了筱崎刨"}, {"m3u8": "https://videozm.whqhyg.com:8091/20201111/ZzUnEFY7/index.m3u8", "img": "https://img2.minqingguancha.com:8099/z-t-img/YST-189.jpg", "title": "YST-189从现在开始一直睡到姐姐完全堕落为止桐谷尚"}, {"m3u8": "https://videozm.whqhyg.com:8091/20201109/FNSHUiJw/index.m3u8", "img": "https://img2.minqingguancha.com:8099/z-t-img/EIKI-096.jpg", "title": "EIKI-096超美型齐全的傲黛丽洋基姑娘奇0波掉油性别！通野未帆"}, {"m3u8": "https://videozm.whqhyg.com:8091/20201109/luw0rLdk/index.m3u8", "img": "https://img2.minqingguancha.com:8099/z-t-img/FAA-303.jpg", "title": "FAA-303在男士美容的圣地池袋潜入繁盛的商店桐嶋りの了！！？"}]