[{"m3u8": "https://videojccdn.wzj9.com:8091/20201207/hjbb00067-Part-4/index.m3u8", "img": "https://jc.8f23aa8.com/2020/02/hjbb00067.jpg", "title": "HJBB-067 2on2コンプリートBOX16時間-D"}, {"m3u8": "https://videojccdn.wzj9.com:8091/20201207/hjbb00067-Part-3/index.m3u8", "img": "https://jc.8f23aa8.com/2020/02/hjbb00067.jpg", "title": "HJBB-067 2on2コンプリートBOX16時間-C"}, {"m3u8": "https://videozm.whqhyg.com:8091/20201203/OLJkM2Ul/index.m3u8", "img": "https://img2.minqingguancha.com:8099/z-t-img/USBA-007.jpg", "title": "USBA-007春药BDSM清秀的年轻妻子成为淫乱的野兽的记录有坂深雪"}, {"m3u8": "https://videozm.whqhyg.com:8091/20201203/kZ6sQDTK/index.m3u8", "img": "https://img2.minqingguancha.com:8099/z-t-img/GS-264.jpg", "title": "GS-264未成年人(189)投稿·制服生拍05"}, {"m3u8": "https://videozm.whqhyg.com:8091/20201203/uJBuGtNE/index.m3u8", "img": "https://img2.minqingguancha.com:8099/z-t-img/VEC-365.jpg", "title": "VEC-365被妻子的女朋友盯上了我不能拒绝中出的风间由美"}, {"m3u8": "https://videozm.whqhyg.com:8091/20201203/nYH1Rshi/index.m3u8", "img": "https://img2.minqingguancha.com:8099/z-t-img/SPRD-1152.jpg", "title": "SPRD-1152比再婚对象之前年长的老婆还是算了吧。 福田由贵"}, {"m3u8": "https://videozm.whqhyg.com:8091/20201203/YFcnQByk/index.m3u8", "img": "https://img2.minqingguancha.com:8099/z-t-img/HBAD-481.jpg", "title": "HBAD-481桃尻寡妇亲属棒的俘虏成为人生最大的追击升天凛音"}, {"m3u8": "https://videozm.whqhyg.com:8091/20201203/VozIv4CO/index.m3u8", "img": "https://img2.minqingguancha.com:8099/z-t-img/SPRD-1154.jpg", "title": "SPRD-1154我是三十岁的阿姨，是个童贞。 袖川弥生(弥生)"}, {"m3u8": "https://videozm.whqhyg.com:8091/20201203/ITBtawg1/index.m3u8", "img": "https://img2.minqingguancha.com:8099/z-t-img/SPRD-1156.jpg", "title": "SPRD-1156女婿抱着岳母 槇原あや"}, {"m3u8": "https://videozm.whqhyg.com:8091/20201203/wCVSq5rf/index.m3u8", "img": "https://img2.minqingguancha.com:8099/z-t-img/GS-263.jpg", "title": "GS-263未成年人(1888)制服亨特03"}, {"m3u8": "https://videozm.whqhyg.com:8091/20201203/EcXzOowX/index.m3u8", "img": "https://img2.minqingguancha.com:8099/z-t-img/SDAM-019.jpg", "title": "SDAM-019“我可以和你的妻子搭讪吗？ 凛音とうか"}, {"m3u8": "https://videozm.whqhyg.com:8091/20201203/i5E2zdrj/index.m3u8", "img": "https://img2.minqingguancha.com:8099/z-t-img/NASH-085.jpg", "title": "NASH-085 妈妈朋友强奸 澤村レイコ"}, {"m3u8": "https://videozm.whqhyg.com:8091/20201203/JzVX5Hln/index.m3u8", "img": "https://img2.minqingguancha.com:8099/z-t-img/HBAD-482.jpg", "title": "HBAD-482丧服下隐藏的肉欲·寡妇的渴欲"}, {"m3u8": "https://videozm.whqhyg.com:8091/20201203/4Xqi08yX/index.m3u8", "img": "https://img2.minqingguancha.com:8099/z-t-img/SPRD-1155.jpg", "title": "SPRD-1155附近清秀的人妻郡司结子"}, {"m3u8": "https://videozm.whqhyg.com:8091/20201203/vGRwT0s4/index.m3u8", "img": "https://img2.minqingguancha.com:8099/z-t-img/NHDTB-282.jpg", "title": "NHDTB-282强震动阴茎拧入袭被超侵犯连声音都说不出的女生 皆月ひかる"}, {"m3u8": "https://videozm.whqhyg.com:8091/20201203/MBcwqhLt/index.m3u8", "img": "https://img2.minqingguancha.com:8099/z-t-img/XMOM-05.jpg", "title": "XMOM-05 维罗基斯夫人的浓厚吻和中出SEX泽村玲子"}, {"m3u8": "https://videozm.whqhyg.com:8091/20201203/4LapLvqI/index.m3u8", "img": "https://img2.minqingguancha.com:8099/z-t-img/RCTD-232.jpg", "title": "RCTD-232儿子的话就试试姐姐母亲祖母的裸体猜猜！真白ここ"}, {"m3u8": "https://videozm.whqhyg.com:8091/20201203/eRteClTz/index.m3u8", "img": "https://img2.minqingguancha.com:8099/z-t-img/SPRD-1157.jpg", "title": "SPRD-1157小恶魔媳妇友桥本丽华"}, {"m3u8": "https://videozm.whqhyg.com:8091/20201203/n5vKK5Tv/index.m3u8", "img": "https://img2.minqingguancha.com:8099/z-t-img/NASH-086.jpg", "title": "NASH-086最讨厌的亲属(继父，姐夫)用力被犯的媳妇 近親相姦"}, {"m3u8": "https://videozm.whqhyg.com:8091/20201203/pjXirIZF/index.m3u8", "img": "https://img2.minqingguancha.com:8099/z-t-img/IENF-010.jpg", "title": "IENF-010因为潮吹使我的房间变得乱七八糟的，佐久間恵美"}, {"m3u8": "https://videozm.whqhyg.com:8091/20201203/y3NDtZ6m/index.m3u8", "img": "https://img2.minqingguancha.com:8099/z-t-img/HUNTA-614.jpg", "title": "HUNTA-614新生的岳母又年轻又漂亮，超巨乳。 木村成美"}, {"m3u8": "https://videozm.whqhyg.com:8091/20201203/cdHhvhmh/index.m3u8", "img": "https://img2.minqingguancha.com:8099/z-t-img/GDHH-156.jpg", "title": "GDHH-156和同班同学的女生同居两天一夜！？ 水卜麻衣奈"}, {"m3u8": "https://videojccdn.wzj9.com:8091/20201208/h_606mlw03508/index.m3u8", "img": "https://jc.8f23aa8.com/2020/02/h_606mlw03508.jpg", "title": "MLW-3508 解禁！中出し爆乳 志村玲子"}, {"m3u8": "https://videojccdn.wzj9.com:8091/20201208/h_606mlw03504/index.m3u8", "img": "https://jc.8f23aa8.com/2020/02/h_606mlw03504.jpg", "title": "MLW-3504 巨乳熟女の中出し天国・発情期"}, {"m3u8": "https://videojccdn.wzj9.com:8091/20201208/h_606mlw03503/index.m3u8", "img": "https://jc.8f23aa8.com/2020/02/h_606mlw03503.jpg", "title": "MLW-3503 爆乳妻は2穴中出しがお好き！"}, {"m3u8": "https://videojccdn.wzj9.com:8091/20201208/h_606mlw03501/index.m3u8", "img": "https://jc.8f23aa8.com/2020/02/h_606mlw03501.jpg", "title": "MLW-3501 ぶっかけ巨乳熟女 中出し痴態 横山みれい"}, {"m3u8": "https://videojccdn.wzj9.com:8091/20201208/h_606mlw02012/index.m3u8", "img": "https://jc.8f23aa8.com/2020/02/h_606mlw02012.jpg", "title": "MLW-2012 ぼくの美人で肉食系姉さん ～性教育で潮吹きまくり！"}, {"m3u8": "https://videozm.whqhyg.com:8091/20201204/pngJzxKn/index.m3u8", "img": "https://img2.minqingguancha.com:8099/z-t-img/NHDTB-274.jpg", "title": "NHDTB-274叔叔开发了侄女，对第一次的快感发情，山井すず"}, {"m3u8": "https://videozm.whqhyg.com:8091/20201204/IXAfzk1v/index.m3u8", "img": "https://img2.minqingguancha.com:8099/z-t-img/SCPX-361.jpg", "title": "SCPX-361巨乳的同事意外地变成了相间的我。 宮崎あや"}, {"m3u8": "https://videozm.whqhyg.com:8091/20201204/4FlvQiHT/index.m3u8", "img": "https://img2.minqingguancha.com:8099/z-t-img/SPRD-1151.jpg", "title": "SPRD-1151岳母，比女老婆好多了。 相浦茉莉花"}, {"m3u8": "https://videozm.whqhyg.com:8091/20201204/a1l2jQ5E/index.m3u8", "img": "https://img2.minqingguancha.com:8099/z-t-img/SPRD-1153.jpg", "title": "SPRD-1153崩塌亲子爱森下美绪"}, {"m3u8": "https://videozm.whqhyg.com:8091/20201204/D96nIqwN/index.m3u8", "img": "https://img2.minqingguancha.com:8099/z-t-img/TURU-045.jpg", "title": "TURU-045 姑姑之家绝伦外甥少年当天内特莱"}, {"m3u8": "https://videozm.whqhyg.com:8091/20201204/s2amR9I7/index.m3u8", "img": "https://img2.minqingguancha.com:8099/z-t-img/UMSO-253.jpg", "title": "UMSO-253被指名前往的目的地是男朋友的好友家！？ 椎葉みくる"}, {"m3u8": "https://videozm.whqhyg.com:8091/20201204/skHhVYtK/index.m3u8", "img": "https://img2.minqingguancha.com:8099/z-t-img/MKMP-279.jpg", "title": "MKMP-279佐仓羁绊Kawai Carcosplay"}, {"m3u8": "https://videozm.whqhyg.com:8091/20201204/G4HoTtGa/index.m3u8", "img": "https://img2.minqingguancha.com:8099/z-t-img/MKMP-280.jpg", "title": "MKMP-280梦照歌3rd“你的光谱”"}, {"m3u8": "https://videozm.whqhyg.com:8091/20201204/QkXz3Szq/index.m3u8", "img": "https://img2.minqingguancha.com:8099/z-t-img/MKMP-281.jpg", "title": "MKMP-281中出10连发枢木葵"}]